lang_font_map/__init__.py
lang_font_map/fonts_map.py
lang_font_map-0.1.dist-info/licenses/LICENSE
lang_font_map-0.1.dist-info/METADATA
lang_font_map-0.1.dist-info/WHEEL
lang_font_map-0.1.dist-info/top_level.txt
lang_font_map-0.1.dist-info/RECORD
