Metadata-Version: 2.4
Name: lang_font_map
Version: 0.1
Summary: Language to Google Fonts mapping for various scripts
Author: Your Name
Classifier: Programming Language :: Python :: 3
Requires-Python: >=3.6
License-File: LICENSE
Dynamic: author
Dynamic: classifier
Dynamic: license-file
Dynamic: requires-python
Dynamic: summary
